tests/__init__.py
tests/test_clip.py
tests/test_composition.py
tests/test_utils.py
vidpy/__init__.py
vidpy/camera.py
vidpy/clip.py
vidpy/color.py
vidpy/composition.py
vidpy/config.py
vidpy/effects.py
vidpy/text.py
vidpy/utils.py
vidpy-0.1.9.dist-info/DESCRIPTION.rst
vidpy-0.1.9.dist-info/LICENSE.txt
vidpy-0.1.9.dist-info/METADATA
vidpy-0.1.9.dist-info/RECORD
vidpy-0.1.9.dist-info/WHEEL
vidpy-0.1.9.dist-info/metadata.json
vidpy-0.1.9.dist-info/top_level.txt
