Metadata-Version: 1.0
Name: vidpy
Version: 0.1.9
Summary: Video editing and compositing in Python
Home-page: https://antiboredom.github.io/vidpy
Author: Sam Lavigne
Author-email: lavigne@saaaam.com
License: MIT
Platform: UNKNOWN
